[
  {
    "date": "Fri, 27 Feb 2026",
    "draw_number": "4160",
    "winning_numbers": [
      "5",
      "9",
      "20",
      "23",
      "45",
      "46"
    ],
    "additional_number": "7",
    "jackpot": "$12,000,001",
    "group_prizes": [
      {
        "group": "Group 1",
        "amount": "$4,000,000",
        "shares": "3"
      },
      {
        "group": "Group 2",
        "amount": "$77,132",
        "shares": "32"
      },
      {
        "group": "Group 3",
        "amount": "$1,566",
        "shares": "1,084"
      },
      {
        "group": "Group 4",
        "amount": "$286",
        "shares": "3,244"
      },
      {
        "group": "Group 5",
        "amount": "$50",
        "shares": "55,832"
      },
      {
        "group": "Group 6",
        "amount": "$25",
        "shares": "86,184"
      },
      {
        "group": "Group 7",
        "amount": "$10",
        "shares": "993,740"
      }
    ]
  },
  {
    "date": "Mon, 23 Feb 2026",
    "draw_number": "4159",
    "winning_numbers": [
      "24",
      "26",
      "30",
      "32",
      "37",
      "47"
    ],
    "additional_number": "2",
    "jackpot": "$1,787,436",
    "group_prizes": [
      {
        "group": "Group 1",
        "amount": "$893,718",
        "shares": "2"
      },
      {
        "group": "Group 2",
        "amount": "$188,152",
        "shares": "2"
      },
      {
        "group": "Group 3",
        "amount": "$2,562",
        "shares": "101"
      },
      {
        "group": "Group 4",
        "amount": "$453",
        "shares": "312"
      },
      {
        "group": "Group 5",
        "amount": "$50",
        "shares": "6,204"
      },
      {
        "group": "Group 6",
        "amount": "$25",
        "shares": "9,583"
      },
      {
        "group": "Group 7",
        "amount": "$10",
        "shares": "122,832"
      }
    ]
  },
  {
    "date": "Thu, 19 Feb 2026",
    "draw_number": "4158",
    "winning_numbers": [
      "8",
      "16",
      "17",
      "34",
      "38",
      "48"
    ],
    "additional_number": "25",
    "jackpot": "$1,474,367",
    "group_prizes": [
      {
        "group": "Group 1",
        "amount": "$1,474,367",
        "shares": "1"
      },
      {
        "group": "Group 2",
        "amount": "$62,079",
        "shares": "5"
      },
      {
        "group": "Group 3",
        "amount": "$1,482",
        "shares": "144"
      },
      {
        "group": "Group 4",
        "amount": "$387",
        "shares": "301"
      },
      {
        "group": "Group 5",
        "amount": "$50",
        "shares": "6,849"
      },
      {
        "group": "Group 6",
        "amount": "$25",
        "shares": "8,379"
      },
      {
        "group": "Group 7",
        "amount": "$10",
        "shares": "123,806"
      }
    ]
  },
  {
    "date": "Mon, 16 Feb 2026",
    "draw_number": "4157",
    "winning_numbers": [
      "13",
      "24",
      "28",
      "34",
      "37",
      "44"
    ],
    "additional_number": "29",
    "jackpot": "$1,487,895",
    "group_prizes": [
      {
        "group": "Group 1",
        "amount": "$1,487,895",
        "shares": "1"
      },
      {
        "group": "Group 2",
        "amount": "$104,414",
        "shares": "3"
      },
      {
        "group": "Group 3",
        "amount": "$1,766",
        "shares": "122"
      },
      {
        "group": "Group 4",
        "amount": "$388",
        "shares": "303"
      },
      {
        "group": "Group 5",
        "amount": "$50",
        "shares": "6,113"
      },
      {
        "group": "Group 6",
        "amount": "$25",
        "shares": "8,114"
      },
      {
        "group": "Group 7",
        "amount": "$10",
        "shares": "111,326"
      }
    ]
  },
  {
    "date": "Fri, 13 Feb 2026",
    "draw_number": "4156",
    "winning_numbers": [
      "10",
      "15",
      "25",
      "43",
      "45",
      "49"
    ],
    "additional_number": "4",
    "jackpot": "$6,188,268",
    "group_prizes": [
      {
        "group": "Group 1",
        "amount": "$6,188,268",
        "shares": "1"
      },
      {
        "group": "Group 2",
        "amount": "$86,853",
        "shares": "15"
      },
      {
        "group": "Group 3",
        "amount": "$1,795",
        "shares": "499"
      },
      {
        "group": "Group 4",
        "amount": "$379",
        "shares": "1,292"
      },
      {
        "group": "Group 5",
        "amount": "$50",
        "shares": "26,860"
      },
      {
        "group": "Group 6",
        "amount": "$25",
        "shares": "35,730"
      },
      {
        "group": "Group 7",
        "amount": "$10",
        "shares": "492,757"
      }
    ]
  },
  {
    "date": "Mon, 09 Feb 2026",
    "draw_number": "4155",
    "winning_numbers": [
      "10",
      "15",
      "29",
      "31",
      "33",
      "49"
    ],
    "additional_number": "30",
    "jackpot": "$6,527,079",
    "group_prizes": [
      {
        "group": "Group 1",
        "amount": "$3,263,539",
        "shares": "2"
      },
      {
        "group": "Group 2",
        "amount": "$231,713",
        "shares": "3"
      },
      {
        "group": "Group 3",
        "amount": "$1,079",
        "shares": "443"
      },
      {
        "group": "Group 4",
        "amount": "$395",
        "shares": "660"
      },
      {
        "group": "Group 5",
        "amount": "$50",
        "shares": "15,654"
      },
      {
        "group": "Group 6",
        "amount": "$25",
        "shares": "21,400"
      },
      {
        "group": "Group 7",
        "amount": "$10",
        "shares": "277,069"
      }
    ]
  },
  {
    "date": "Thu, 05 Feb 2026",
    "draw_number": "4154",
    "winning_numbers": [
      "6",
      "18",
      "24",
      "26",
      "36",
      "48"
    ],
    "additional_number": "5",
    "jackpot": "$3,225,180",
    "group_prizes": [
      {
        "group": "Group 1",
        "amount": "-",
        "shares": "-"
      },
      {
        "group": "Group 2",
        "amount": "$200,575",
        "shares": "2"
      },
      {
        "group": "Group 3",
        "amount": "$1,232",
        "shares": "224"
      },
      {
        "group": "Group 4",
        "amount": "$322",
        "shares": "468"
      },
      {
        "group": "Group 5",
        "amount": "$50",
        "shares": "9,237"
      },
      {
        "group": "Group 6",
        "amount": "$25",
        "shares": "13,654"
      },
      {
        "group": "Group 7",
        "amount": "$10",
        "shares": "154,628"
      }
    ]
  },
  {
    "date": "Mon, 02 Feb 2026",
    "draw_number": "4153",
    "winning_numbers": [
      "4",
      "19",
      "40",
      "41",
      "46",
      "47"
    ],
    "additional_number": "20",
    "jackpot": "$1,319,721",
    "group_prizes": [
      {
        "group": "Group 1",
        "amount": "-",
        "shares": "-"
      },
      {
        "group": "Group 2",
        "amount": "$69,460",
        "shares": "4"
      },
      {
        "group": "Group 3",
        "amount": "$2,147",
        "shares": "89"
      },
      {
        "group": "Group 4",
        "amount": "$464",
        "shares": "225"
      },
      {
        "group": "Group 5",
        "amount": "$50",
        "shares": "5,139"
      },
      {
        "group": "Group 6",
        "amount": "$25",
        "shares": "6,609"
      },
      {
        "group": "Group 7",
        "amount": "$10",
        "shares": "91,256"
      }
    ]
  },
  {
    "date": "Thu, 29 Jan 2026",
    "draw_number": "4152",
    "winning_numbers": [
      "11",
      "13",
      "16",
      "31",
      "42",
      "48"
    ],
    "additional_number": "21",
    "jackpot": "$13,524,372",
    "group_prizes": [
      {
        "group": "Group 1",
        "amount": "$2,254,062",
        "shares": "6"
      },
      {
        "group": "Group 2",
        "amount": "$123,040",
        "shares": "13"
      },
      {
        "group": "Group 3",
        "amount": "$1,716",
        "shares": "641"
      },
      {
        "group": "Group 4",
        "amount": "$377",
        "shares": "1,592"
      },
      {
        "group": "Group 5",
        "amount": "$50",
        "shares": "31,821"
      },
      {
        "group": "Group 6",
        "amount": "$25",
        "shares": "44,984"
      },
      {
        "group": "Group 7",
        "amount": "$10",
        "shares": "591,751"
      }
    ]
  },
  {
    "date": "Mon, 26 Jan 2026",
    "draw_number": "4151",
    "winning_numbers": [
      "10",
      "11",
      "13",
      "26",
      "32",
      "39"
    ],
    "additional_number": "44",
    "jackpot": "$5,926,661",
    "group_prizes": [
      {
        "group": "Group 1",
        "amount": "-",
        "shares": "-"
      },
      {
        "group": "Group 2",
        "amount": "$56,742",
        "shares": "11"
      },
      {
        "group": "Group 3",
        "amount": "$1,544",
        "shares": "278"
      },
      {
        "group": "Group 4",
        "amount": "$380",
        "shares": "617"
      },
      {
        "group": "Group 5",
        "amount": "$50",
        "shares": "14,163"
      },
      {
        "group": "Group 6",
        "amount": "$25",
        "shares": "15,955"
      },
      {
        "group": "Group 7",
        "amount": "$10",
        "shares": "259,857"
      }
    ]
  },
  {
    "date": "Thu, 22 Jan 2026",
    "draw_number": "4150",
    "winning_numbers": [
      "6",
      "22",
      "27",
      "32",
      "37",
      "44"
    ],
    "additional_number": "19",
    "jackpot": "$2,961,924",
    "group_prizes": [
      {
        "group": "Group 1",
        "amount": "-",
        "shares": "-"
      },
      {
        "group": "Group 2",
        "amount": "$71,065",
        "shares": "5"
      },
      {
        "group": "Group 3",
        "amount": "$1,472",
        "shares": "166"
      },
      {
        "group": "Group 4",
        "amount": "$324",
        "shares": "412"
      },
      {
        "group": "Group 5",
        "amount": "$50",
        "shares": "7,378"
      },
      {
        "group": "Group 6",
        "amount": "$25",
        "shares": "11,070"
      },
      {
        "group": "Group 7",
        "amount": "$10",
        "shares": "131,725"
      }
    ]
  },
  {
    "date": "Mon, 19 Jan 2026",
    "draw_number": "4149",
    "winning_numbers": [
      "4",
      "11",
      "21",
      "23",
      "31",
      "35"
    ],
    "additional_number": "48",
    "jackpot": "$1,274,136",
    "group_prizes": [
      {
        "group": "Group 1",
        "amount": "-",
        "shares": "-"
      },
      {
        "group": "Group 2",
        "amount": "$67,060",
        "shares": "4"
      },
      {
        "group": "Group 3",
        "amount": "$1,740",
        "shares": "106"
      },
      {
        "group": "Group 4",
        "amount": "$430",
        "shares": "234"
      },
      {
        "group": "Group 5",
        "amount": "$50",
        "shares": "6,086"
      },
      {
        "group": "Group 6",
        "amount": "$25",
        "shares": "6,224"
      },
      {
        "group": "Group 7",
        "amount": "$10",
        "shares": "111,119"
      }
    ]
  },
  {
    "date": "Thu, 15 Jan 2026",
    "draw_number": "4148",
    "winning_numbers": [
      "16",
      "32",
      "34",
      "35",
      "36",
      "41"
    ],
    "additional_number": "14",
    "jackpot": "$1,250,153",
    "group_prizes": [
      {
        "group": "Group 1",
        "amount": "$1,250,153",
        "shares": "1"
      },
      {
        "group": "Group 2",
        "amount": "$87,731",
        "shares": "3"
      },
      {
        "group": "Group 3",
        "amount": "$2,034",
        "shares": "89"
      },
      {
        "group": "Group 4",
        "amount": "$424",
        "shares": "233"
      },
      {
        "group": "Group 5",
        "amount": "$50",
        "shares": "4,688"
      },
      {
        "group": "Group 6",
        "amount": "$25",
        "shares": "6,400"
      },
      {
        "group": "Group 7",
        "amount": "$10",
        "shares": "83,224"
      }
    ]
  },
  {
    "date": "Mon, 12 Jan 2026",
    "draw_number": "4147",
    "winning_numbers": [
      "1",
      "9",
      "16",
      "18",
      "35",
      "43"
    ],
    "additional_number": "12",
    "jackpot": "$1,291,824",
    "group_prizes": [
      {
        "group": "Group 1",
        "amount": "$645,912",
        "shares": "2"
      },
      {
        "group": "Group 2",
        "amount": "$135,982",
        "shares": "2"
      },
      {
        "group": "Group 3",
        "amount": "$2,253",
        "shares": "83"
      },
      {
        "group": "Group 4",
        "amount": "$282",
        "shares": "362"
      },
      {
        "group": "Group 5",
        "amount": "$50",
        "shares": "6,022"
      },
      {
        "group": "Group 6",
        "amount": "$25",
        "shares": "10,992"
      },
      {
        "group": "Group 7",
        "amount": "$10",
        "shares": "111,643"
      }
    ]
  },
  {
    "date": "Thu, 08 Jan 2026",
    "draw_number": "4146",
    "winning_numbers": [
      "3",
      "14",
      "15",
      "17",
      "25",
      "27"
    ],
    "additional_number": "31",
    "jackpot": "$2,923,900",
    "group_prizes": [
      {
        "group": "Group 1",
        "amount": "$2,923,900",
        "shares": "1"
      },
      {
        "group": "Group 2",
        "amount": "$45,197",
        "shares": "8"
      },
      {
        "group": "Group 3",
        "amount": "$1,498",
        "shares": "166"
      },
      {
        "group": "Group 4",
        "amount": "$288",
        "shares": "471"
      },
      {
        "group": "Group 5",
        "amount": "$50",
        "shares": "8,693"
      },
      {
        "group": "Group 6",
        "amount": "$25",
        "shares": "11,383"
      },
      {
        "group": "Group 7",
        "amount": "$10",
        "shares": "153,853"
      }
    ]
  },
  {
    "date": "Mon, 05 Jan 2026",
    "draw_number": "4145",
    "winning_numbers": [
      "5",
      "20",
      "35",
      "39",
      "40",
      "49"
    ],
    "additional_number": "27",
    "jackpot": "$1,206,430",
    "group_prizes": [
      {
        "group": "Group 1",
        "amount": "-",
        "shares": "-"
      },
      {
        "group": "Group 2",
        "amount": "$253,986",
        "shares": "1"
      },
      {
        "group": "Group 3",
        "amount": "$2,646",
        "shares": "66"
      },
      {
        "group": "Group 4",
        "amount": "$551",
        "shares": "173"
      },
      {
        "group": "Group 5",
        "amount": "$50",
        "shares": "4,567"
      },
      {
        "group": "Group 6",
        "amount": "$25",
        "shares": "5,737"
      },
      {
        "group": "Group 7",
        "amount": "$10",
        "shares": "86,036"
      }
    ]
  },
  {
    "date": "Fri, 02 Jan 2026",
    "draw_number": "4144",
    "winning_numbers": [
      "11",
      "18",
      "20",
      "32",
      "38",
      "39"
    ],
    "additional_number": "34",
    "jackpot": "$7,960,105",
    "group_prizes": [
      {
        "group": "Group 1",
        "amount": "$2,653,368",
        "shares": "3"
      },
      {
        "group": "Group 2",
        "amount": "$98,578",
        "shares": "17"
      },
      {
        "group": "Group 3",
        "amount": "$1,337",
        "shares": "717"
      },
      {
        "group": "Group 4",
        "amount": "$356",
        "shares": "1,471"
      },
      {
        "group": "Group 5",
        "amount": "$50",
        "shares": "30,529"
      },
      {
        "group": "Group 6",
        "amount": "$25",
        "shares": "39,692"
      },
      {
        "group": "Group 7",
        "amount": "$10",
        "shares": "545,195"
      }
    ]
  },
  {
    "date": "Mon, 29 Dec 2025",
    "draw_number": "4143",
    "winning_numbers": [
      "2",
      "4",
      "22",
      "24",
      "30",
      "33"
    ],
    "additional_number": "49",
    "jackpot": "$1,336,997",
    "group_prizes": [
      {
        "group": "Group 1",
        "amount": "-",
        "shares": "-"
      },
      {
        "group": "Group 2",
        "amount": "-",
        "shares": "-"
      },
      {
        "group": "Group 3",
        "amount": "$1,403",
        "shares": "138"
      },
      {
        "group": "Group 4",
        "amount": "$523",
        "shares": "202"
      },
      {
        "group": "Group 5",
        "amount": "$50",
        "shares": "6,934"
      },
      {
        "group": "Group 6",
        "amount": "$25",
        "shares": "6,472"
      },
      {
        "group": "Group 7",
        "amount": "$10",
        "shares": "115,097"
      }
    ]
  },
  {
    "date": "Thu, 25 Dec 2025",
    "draw_number": "4142",
    "winning_numbers": [
      "3",
      "8",
      "15",
      "28",
      "37",
      "43"
    ],
    "additional_number": "49",
    "jackpot": "$5,573,082",
    "group_prizes": [
      {
        "group": "Group 1",
        "amount": "$5,573,082",
        "shares": "1"
      },
      {
        "group": "Group 2",
        "amount": "$79,770",
        "shares": "7"
      },
      {
        "group": "Group 3",
        "amount": "$1,455",
        "shares": "264"
      },
      {
        "group": "Group 4",
        "amount": "$378",
        "shares": "554"
      },
      {
        "group": "Group 5",
        "amount": "$50",
        "shares": "13,045"
      },
      {
        "group": "Group 6",
        "amount": "$25",
        "shares": "15,282"
      },
      {
        "group": "Group 7",
        "amount": "$10",
        "shares": "236,888"
      }
    ]
  },
  {
    "date": "Mon, 22 Dec 2025",
    "draw_number": "4141",
    "winning_numbers": [
      "4",
      "5",
      "13",
      "22",
      "24",
      "30"
    ],
    "additional_number": "36",
    "jackpot": "$2,920,757",
    "group_prizes": [
      {
        "group": "Group 1",
        "amount": "-",
        "shares": "-"
      },
      {
        "group": "Group 2",
        "amount": "$358,749",
        "shares": "1"
      },
      {
        "group": "Group 3",
        "amount": "$1,228",
        "shares": "201"
      },
      {
        "group": "Group 4",
        "amount": "$421",
        "shares": "320"
      },
      {
        "group": "Group 5",
        "amount": "$50",
        "shares": "9,193"
      },
      {
        "group": "Group 6",
        "amount": "$25",
        "shares": "9,437"
      },
      {
        "group": "Group 7",
        "amount": "$10",
        "shares": "161,082"
      }
    ]
  },
  {
    "date": "Thu, 18 Dec 2025",
    "draw_number": "4140",
    "winning_numbers": [
      "2",
      "14",
      "15",
      "30",
      "31",
      "43"
    ],
    "additional_number": "27",
    "jackpot": "$1,216,701",
    "group_prizes": [
      {
        "group": "Group 1",
        "amount": "-",
        "shares": "-"
      },
      {
        "group": "Group 2",
        "amount": "$128,074",
        "shares": "2"
      },
      {
        "group": "Group 3",
        "amount": "$2,710",
        "shares": "65"
      },
      {
        "group": "Group 4",
        "amount": "$460",
        "shares": "209"
      },
      {
        "group": "Group 5",
        "amount": "$50",
        "shares": "4,577"
      },
      {
        "group": "Group 6",
        "amount": "$25",
        "shares": "6,628"
      },
      {
        "group": "Group 7",
        "amount": "$10",
        "shares": "89,975"
      }
    ]
  },
  {
    "date": "Mon, 15 Dec 2025",
    "draw_number": "4139",
    "winning_numbers": [
      "17",
      "21",
      "22",
      "35",
      "37",
      "42"
    ],
    "additional_number": "9",
    "jackpot": "$1,231,419",
    "group_prizes": [
      {
        "group": "Group 1",
        "amount": "$1,231,419",
        "shares": "1"
      },
      {
        "group": "Group 2",
        "amount": "$86,416",
        "shares": "3"
      },
      {
        "group": "Group 3",
        "amount": "$2,003",
        "shares": "89"
      },
      {
        "group": "Group 4",
        "amount": "$457",
        "shares": "213"
      },
      {
        "group": "Group 5",
        "amount": "$50",
        "shares": "5,169"
      },
      {
        "group": "Group 6",
        "amount": "$25",
        "shares": "6,908"
      },
      {
        "group": "Group 7",
        "amount": "$10",
        "shares": "93,721"
      }
    ]
  },
  {
    "date": "Thu, 11 Dec 2025",
    "draw_number": "4138",
    "winning_numbers": [
      "6",
      "11",
      "20",
      "28",
      "33",
      "43"
    ],
    "additional_number": "16",
    "jackpot": "$2,933,089",
    "group_prizes": [
      {
        "group": "Group 1",
        "amount": "$2,933,089",
        "shares": "1"
      },
      {
        "group": "Group 2",
        "amount": "$88,211",
        "shares": "4"
      },
      {
        "group": "Group 3",
        "amount": "$1,824",
        "shares": "133"
      },
      {
        "group": "Group 4",
        "amount": "$271",
        "shares": "490"
      },
      {
        "group": "Group 5",
        "amount": "$50",
        "shares": "8,457"
      },
      {
        "group": "Group 6",
        "amount": "$25",
        "shares": "11,754"
      },
      {
        "group": "Group 7",
        "amount": "$10",
        "shares": "150,556"
      }
    ]
  },
  {
    "date": "Mon, 08 Dec 2025",
    "draw_number": "4137",
    "winning_numbers": [
      "9",
      "12",
      "15",
      "23",
      "27",
      "47"
    ],
    "additional_number": "45",
    "jackpot": "$1,257,083",
    "group_prizes": [
      {
        "group": "Group 1",
        "amount": "-",
        "shares": "-"
      },
      {
        "group": "Group 2",
        "amount": "$88,217",
        "shares": "3"
      },
      {
        "group": "Group 3",
        "amount": "$1,319",
        "shares": "138"
      },
      {
        "group": "Group 4",
        "amount": "$379",
        "shares": "262"
      },
      {
        "group": "Group 5",
        "amount": "$50",
        "shares": "7,717"
      },
      {
        "group": "Group 6",
        "amount": "$25",
        "shares": "7,183"
      },
      {
        "group": "Group 7",
        "amount": "$10",
        "shares": "131,194"
      }
    ]
  },
  {
    "date": "Thu, 04 Dec 2025",
    "draw_number": "4136",
    "winning_numbers": [
      "1",
      "5",
      "24",
      "36",
      "41",
      "46"
    ],
    "additional_number": "39",
    "jackpot": "$2,911,458",
    "group_prizes": [
      {
        "group": "Group 1",
        "amount": "$2,911,458",
        "shares": "1"
      },
      {
        "group": "Group 2",
        "amount": "$175,916",
        "shares": "2"
      },
      {
        "group": "Group 3",
        "amount": "$2,000",
        "shares": "121"
      },
      {
        "group": "Group 4",
        "amount": "$498",
        "shares": "265"
      },
      {
        "group": "Group 5",
        "amount": "$50",
        "shares": "6,631"
      },
      {
        "group": "Group 6",
        "amount": "$25",
        "shares": "7,747"
      },
      {
        "group": "Group 7",
        "amount": "$10",
        "shares": "123,859"
      }
    ]
  },
  {
    "date": "Mon, 01 Dec 2025",
    "draw_number": "4135",
    "winning_numbers": [
      "2",
      "10",
      "24",
      "35",
      "45",
      "49"
    ],
    "additional_number": "37",
    "jackpot": "$1,240,259",
    "group_prizes": [
      {
        "group": "Group 1",
        "amount": "-",
        "shares": "-"
      },
      {
        "group": "Group 2",
        "amount": "$261,108",
        "shares": "1"
      },
      {
        "group": "Group 3",
        "amount": "$2,138",
        "shares": "84"
      },
      {
        "group": "Group 4",
        "amount": "$444",
        "shares": "221"
      },
      {
        "group": "Group 5",
        "amount": "$50",
        "shares": "5,030"
      },
      {
        "group": "Group 6",
        "amount": "$25",
        "shares": "6,161"
      },
      {
        "group": "Group 7",
        "amount": "$10",
        "shares": "92,173"
      }
    ]
  },
  {
    "date": "Thu, 27 Nov 2025",
    "draw_number": "4134",
    "winning_numbers": [
      "6",
      "8",
      "17",
      "28",
      "32",
      "46"
    ],
    "additional_number": "16",
    "jackpot": "$2,867,460",
    "group_prizes": [
      {
        "group": "Group 1",
        "amount": "$2,867,460",
        "shares": "1"
      },
      {
        "group": "Group 2",
        "amount": "$171,078",
        "shares": "2"
      },
      {
        "group": "Group 3",
        "amount": "$1,657",
        "shares": "142"
      },
      {
        "group": "Group 4",
        "amount": "$352",
        "shares": "365"
      },
      {
        "group": "Group 5",
        "amount": "$50",
        "shares": "7,934"
      },
      {
        "group": "Group 6",
        "amount": "$25",
        "shares": "11,449"
      },
      {
        "group": "Group 7",
        "amount": "$10",
        "shares": "146,499"
      }
    ]
  },
  {
    "date": "Mon, 24 Nov 2025",
    "draw_number": "4133",
    "winning_numbers": [
      "8",
      "25",
      "27",
      "34",
      "45",
      "47"
    ],
    "additional_number": "19",
    "jackpot": "$1,242,224",
    "group_prizes": [
      {
        "group": "Group 1",
        "amount": "-",
        "shares": "-"
      },
      {
        "group": "Group 2",
        "amount": "$130,761",
        "shares": "2"
      },
      {
        "group": "Group 3",
        "amount": "$2,366",
        "shares": "76"
      },
      {
        "group": "Group 4",
        "amount": "$368",
        "shares": "267"
      },
      {
        "group": "Group 5",
        "amount": "$50",
        "shares": "4,681"
      },
      {
        "group": "Group 6",
        "amount": "$25",
        "shares": "7,403"
      },
      {
        "group": "Group 7",
        "amount": "$10",
        "shares": "89,557"
      }
    ]
  },
  {
    "date": "Thu, 20 Nov 2025",
    "draw_number": "4132",
    "winning_numbers": [
      "11",
      "13",
      "22",
      "31",
      "47",
      "49"
    ],
    "additional_number": "39",
    "jackpot": "$2,993,324",
    "group_prizes": [
      {
        "group": "Group 1",
        "amount": "$1,496,662",
        "shares": "2"
      },
      {
        "group": "Group 2",
        "amount": "$181,882",
        "shares": "2"
      },
      {
        "group": "Group 3",
        "amount": "$2,017",
        "shares": "124"
      },
      {
        "group": "Group 4",
        "amount": "$432",
        "shares": "316"
      },
      {
        "group": "Group 5",
        "amount": "$50",
        "shares": "7,851"
      },
      {
        "group": "Group 6",
        "amount": "$25",
        "shares": "9,182"
      },
      {
        "group": "Group 7",
        "amount": "$10",
        "shares": "141,063"
      }
    ]
  },
  {
    "date": "Mon, 17 Nov 2025",
    "draw_number": "4131",
    "winning_numbers": [
      "3",
      "9",
      "12",
      "18",
      "19",
      "34"
    ],
    "additional_number": "24",
    "jackpot": "$1,265,445",
    "group_prizes": [
      {
        "group": "Group 1",
        "amount": "-",
        "shares": "-"
      },
      {
        "group": "Group 2",
        "amount": "$66,603",
        "shares": "4"
      },
      {
        "group": "Group 3",
        "amount": "$1,078",
        "shares": "170"
      },
      {
        "group": "Group 4",
        "amount": "$202",
        "shares": "495"
      },
      {
        "group": "Group 5",
        "amount": "$50",
        "shares": "9,291"
      },
      {
        "group": "Group 6",
        "amount": "$25",
        "shares": "10,474"
      },
      {
        "group": "Group 7",
        "amount": "$10",
        "shares": "143,566"
      }
    ]
  },
  {
    "date": "Thu, 13 Nov 2025",
    "draw_number": "4130",
    "winning_numbers": [
      "6",
      "13",
      "18",
      "22",
      "34",
      "35"
    ],
    "additional_number": "40",
    "jackpot": "$3,039,287",
    "group_prizes": [
      {
        "group": "Group 1",
        "amount": "$3,039,287",
        "shares": "1"
      },
      {
        "group": "Group 2",
        "amount": "$92,324",
        "shares": "4"
      },
      {
        "group": "Group 3",
        "amount": "$1,776",
        "shares": "143"
      },
      {
        "group": "Group 4",
        "amount": "$389",
        "shares": "356"
      },
      {
        "group": "Group 5",
        "amount": "$50",
        "shares": "8,250"
      },
      {
        "group": "Group 6",
        "amount": "$25",
        "shares": "9,816"
      },
      {
        "group": "Group 7",
        "amount": "$10",
        "shares": "152,602"
      }
    ]
  },
  {
    "date": "Mon, 10 Nov 2025",
    "draw_number": "4129",
    "winning_numbers": [
      "2",
      "11",
      "12",
      "19",
      "25",
      "36"
    ],
    "additional_number": "16",
    "jackpot": "$1,285,138",
    "group_prizes": [
      {
        "group": "Group 1",
        "amount": "-",
        "shares": "-"
      },
      {
        "group": "Group 2",
        "amount": "$67,639",
        "shares": "4"
      },
      {
        "group": "Group 3",
        "amount": "$1,170",
        "shares": "159"
      },
      {
        "group": "Group 4",
        "amount": "$241",
        "shares": "421"
      },
      {
        "group": "Group 5",
        "amount": "$50",
        "shares": "8,778"
      },
      {
        "group": "Group 6",
        "amount": "$25",
        "shares": "10,776"
      },
      {
        "group": "Group 7",
        "amount": "$10",
        "shares": "140,314"
      }
    ]
  },
  {
    "date": "Thu, 06 Nov 2025",
    "draw_number": "4128",
    "winning_numbers": [
      "3",
      "20",
      "24",
      "29",
      "32",
      "44"
    ],
    "additional_number": "46",
    "jackpot": "$12,286,495",
    "group_prizes": [
      {
        "group": "Group 1",
        "amount": "$12,286,496",
        "shares": "1"
      },
      {
        "group": "Group 2",
        "amount": "$123,444",
        "shares": "11"
      },
      {
        "group": "Group 3",
        "amount": "$1,569",
        "shares": "595"
      },
      {
        "group": "Group 4",
        "amount": "$417",
        "shares": "1,224"
      },
      {
        "group": "Group 5",
        "amount": "$50",
        "shares": "28,822"
      },
      {
        "group": "Group 6",
        "amount": "$25",
        "shares": "33,956"
      },
      {
        "group": "Group 7",
        "amount": "$10",
        "shares": "516,449"
      }
    ]
  },
  {
    "date": "Mon, 03 Nov 2025",
    "draw_number": "4127",
    "winning_numbers": [
      "10",
      "19",
      "22",
      "34",
      "39",
      "43"
    ],
    "additional_number": "35",
    "jackpot": "$5,836,580",
    "group_prizes": [
      {
        "group": "Group 1",
        "amount": "-",
        "shares": "-"
      },
      {
        "group": "Group 2",
        "amount": "$67,235",
        "shares": "9"
      },
      {
        "group": "Group 3",
        "amount": "$1,547",
        "shares": "269"
      },
      {
        "group": "Group 4",
        "amount": "$317",
        "shares": "718"
      },
      {
        "group": "Group 5",
        "amount": "$50",
        "shares": "13,781"
      },
      {
        "group": "Group 6",
        "amount": "$25",
        "shares": "17,405"
      },
      {
        "group": "Group 7",
        "amount": "$10",
        "shares": "232,947"
      }
    ]
  },
  {
    "date": "Thu, 30 Oct 2025",
    "draw_number": "4126",
    "winning_numbers": [
      "1",
      "5",
      "31",
      "34",
      "38",
      "45"
    ],
    "additional_number": "21",
    "jackpot": "$2,962,292",
    "group_prizes": [
      {
        "group": "Group 1",
        "amount": "-",
        "shares": "-"
      },
      {
        "group": "Group 2",
        "amount": "$360,231",
        "shares": "1"
      },
      {
        "group": "Group 3",
        "amount": "$1,966",
        "shares": "126"
      },
      {
        "group": "Group 4",
        "amount": "$468",
        "shares": "289"
      },
      {
        "group": "Group 5",
        "amount": "$50",
        "shares": "6,630"
      },
      {
        "group": "Group 6",
        "amount": "$25",
        "shares": "9,228"
      },
      {
        "group": "Group 7",
        "amount": "$10",
        "shares": "133,250"
      }
    ]
  },
  {
    "date": "Mon, 27 Oct 2025",
    "draw_number": "4125",
    "winning_numbers": [
      "4",
      "12",
      "14",
      "24",
      "36",
      "38"
    ],
    "additional_number": "17",
    "jackpot": "$1,251,199",
    "group_prizes": [
      {
        "group": "Group 1",
        "amount": "-",
        "shares": "-"
      },
      {
        "group": "Group 2",
        "amount": "$131,706",
        "shares": "2"
      },
      {
        "group": "Group 3",
        "amount": "$1,776",
        "shares": "102"
      },
      {
        "group": "Group 4",
        "amount": "$482",
        "shares": "205"
      },
      {
        "group": "Group 5",
        "amount": "$50",
        "shares": "5,325"
      },
      {
        "group": "Group 6",
        "amount": "$25",
        "shares": "7,342"
      },
      {
        "group": "Group 7",
        "amount": "$10",
        "shares": "99,766"
      }
    ]
  },
  {
    "date": "Thu, 23 Oct 2025",
    "draw_number": "4124",
    "winning_numbers": [
      "7",
      "14",
      "17",
      "18",
      "31",
      "38"
    ],
    "additional_number": "46",
    "jackpot": "$12,427,689",
    "group_prizes": [
      {
        "group": "Group 1",
        "amount": "$4,142,563",
        "shares": "3"
      },
      {
        "group": "Group 2",
        "amount": "$139,191",
        "shares": "10"
      },
      {
        "group": "Group 3",
        "amount": "$1,567",
        "shares": "611"
      },
      {
        "group": "Group 4",
        "amount": "$343",
        "shares": "1,525"
      },
      {
        "group": "Group 5",
        "amount": "$50",
        "shares": "32,674"
      },
      {
        "group": "Group 6",
        "amount": "$25",
        "shares": "37,588"
      },
      {
        "group": "Group 7",
        "amount": "$10",
        "shares": "577,951"
      }
    ]
  },
  {
    "date": "Mon, 20 Oct 2025",
    "draw_number": "4123",
    "winning_numbers": [
      "3",
      "10",
      "13",
      "15",
      "32",
      "37"
    ],
    "additional_number": "8",
    "jackpot": "$5,816,118",
    "group_prizes": [
      {
        "group": "Group 1",
        "amount": "-",
        "shares": "-"
      },
      {
        "group": "Group 2",
        "amount": "$58,728",
        "shares": "10"
      },
      {
        "group": "Group 3",
        "amount": "$1,690",
        "shares": "239"
      },
      {
        "group": "Group 4",
        "amount": "$312",
        "shares": "707"
      },
      {
        "group": "Group 5",
        "amount": "$50",
        "shares": "13,012"
      },
      {
        "group": "Group 6",
        "amount": "$25",
        "shares": "21,561"
      },
      {
        "group": "Group 7",
        "amount": "$10",
        "shares": "239,985"
      }
    ]
  },
  {
    "date": "Thu, 16 Oct 2025",
    "draw_number": "4122",
    "winning_numbers": [
      "2",
      "4",
      "8",
      "19",
      "35",
      "39"
    ],
    "additional_number": "7",
    "jackpot": "$3,026,562",
    "group_prizes": [
      {
        "group": "Group 1",
        "amount": "-",
        "shares": "-"
      },
      {
        "group": "Group 2",
        "amount": "$90,466",
        "shares": "4"
      },
      {
        "group": "Group 3",
        "amount": "$1,693",
        "shares": "147"
      },
      {
        "group": "Group 4",
        "amount": "$275",
        "shares": "494"
      },
      {
        "group": "Group 5",
        "amount": "$50",
        "shares": "8,453"
      },
      {
        "group": "Group 6",
        "amount": "$25",
        "shares": "14,616"
      },
      {
        "group": "Group 7",
        "amount": "$10",
        "shares": "152,801"
      }
    ]
  },
  {
    "date": "Mon, 13 Oct 2025",
    "draw_number": "4121",
    "winning_numbers": [
      "5",
      "31",
      "33",
      "34",
      "38",
      "46"
    ],
    "additional_number": "39",
    "jackpot": "$1,307,713",
    "group_prizes": [
      {
        "group": "Group 1",
        "amount": "-",
        "shares": "-"
      },
      {
        "group": "Group 2",
        "amount": "$275,308",
        "shares": "1"
      },
      {
        "group": "Group 3",
        "amount": "$2,491",
        "shares": "76"
      },
      {
        "group": "Group 4",
        "amount": "$405",
        "shares": "255"
      },
      {
        "group": "Group 5",
        "amount": "$50",
        "shares": "4,664"
      },
      {
        "group": "Group 6",
        "amount": "$25",
        "shares": "6,757"
      },
      {
        "group": "Group 7",
        "amount": "$10",
        "shares": "92,563"
      }
    ]
  },
  {
    "date": "Thu, 09 Oct 2025",
    "draw_number": "4120",
    "winning_numbers": [
      "13",
      "14",
      "19",
      "22",
      "31",
      "42"
    ],
    "additional_number": "41",
    "jackpot": "$5,979,660",
    "group_prizes": [
      {
        "group": "Group 1",
        "amount": "$5,979,660",
        "shares": "1"
      },
      {
        "group": "Group 2",
        "amount": "$150,222",
        "shares": "4"
      },
      {
        "group": "Group 3",
        "amount": "$1,804",
        "shares": "229"
      },
      {
        "group": "Group 4",
        "amount": "$358",
        "shares": "631"
      },
      {
        "group": "Group 5",
        "amount": "$50",
        "shares": "12,644"
      },
      {
        "group": "Group 6",
        "amount": "$25",
        "shares": "16,702"
      },
      {
        "group": "Group 7",
        "amount": "$10",
        "shares": "228,771"
      }
    ]
  },
  {
    "date": "Mon, 06 Oct 2025",
    "draw_number": "4119",
    "winning_numbers": [
      "10",
      "15",
      "22",
      "31",
      "42",
      "48"
    ],
    "additional_number": "4",
    "jackpot": "$3,125,455",
    "group_prizes": [
      {
        "group": "Group 1",
        "amount": "-",
        "shares": "-"
      },
      {
        "group": "Group 2",
        "amount": "$79,158",
        "shares": "5"
      },
      {
        "group": "Group 3",
        "amount": "$2,568",
        "shares": "106"
      },
      {
        "group": "Group 4",
        "amount": "$341",
        "shares": "436"
      },
      {
        "group": "Group 5",
        "amount": "$50",
        "shares": "7,877"
      },
      {
        "group": "Group 6",
        "amount": "$25",
        "shares": "11,529"
      },
      {
        "group": "Group 7",
        "amount": "$10",
        "shares": "149,923"
      }
    ]
  },
  {
    "date": "Thu, 02 Oct 2025",
    "draw_number": "4118",
    "winning_numbers": [
      "19",
      "22",
      "26",
      "37",
      "40",
      "46"
    ],
    "additional_number": "14",
    "jackpot": "$1,245,465",
    "group_prizes": [
      {
        "group": "Group 1",
        "amount": "-",
        "shares": "-"
      },
      {
        "group": "Group 2",
        "amount": "$87,402",
        "shares": "3"
      },
      {
        "group": "Group 3",
        "amount": "$2,691",
        "shares": "67"
      },
      {
        "group": "Group 4",
        "amount": "$436",
        "shares": "226"
      },
      {
        "group": "Group 5",
        "amount": "$50",
        "shares": "4,720"
      },
      {
        "group": "Group 6",
        "amount": "$25",
        "shares": "5,751"
      },
      {
        "group": "Group 7",
        "amount": "$10",
        "shares": "84,535"
      }
    ]
  },
  {
    "date": "Mon, 29 Sep 2025",
    "draw_number": "4117",
    "winning_numbers": [
      "15",
      "16",
      "22",
      "34",
      "35",
      "43"
    ],
    "additional_number": "26",
    "jackpot": "$12,291,552",
    "group_prizes": [
      {
        "group": "Group 1",
        "amount": "$6,145,776",
        "shares": "2"
      },
      {
        "group": "Group 2",
        "amount": "$116,415",
        "shares": "12"
      },
      {
        "group": "Group 3",
        "amount": "$1,607",
        "shares": "598"
      },
      {
        "group": "Group 4",
        "amount": "$413",
        "shares": "1,271"
      },
      {
        "group": "Group 5",
        "amount": "$50",
        "shares": "29,887"
      },
      {
        "group": "Group 6",
        "amount": "$25",
        "shares": "38,354"
      },
      {
        "group": "Group 7",
        "amount": "$10",
        "shares": "524,719"
      }
    ]
  },
  {
    "date": "Thu, 25 Sep 2025",
    "draw_number": "4116",
    "winning_numbers": [
      "1",
      "6",
      "9",
      "11",
      "29",
      "36"
    ],
    "additional_number": "12",
    "jackpot": "$5,655,940",
    "group_prizes": [
      {
        "group": "Group 1",
        "amount": "-",
        "shares": "-"
      },
      {
        "group": "Group 2",
        "amount": "$24,231",
        "shares": "23"
      },
      {
        "group": "Group 3",
        "amount": "$1,144",
        "shares": "335"
      },
      {
        "group": "Group 4",
        "amount": "$182",
        "shares": "1,150"
      },
      {
        "group": "Group 5",
        "amount": "$50",
        "shares": "18,652"
      },
      {
        "group": "Group 6",
        "amount": "$25",
        "shares": "27,569"
      },
      {
        "group": "Group 7",
        "amount": "$10",
        "shares": "284,723"
      }
    ]
  },
  {
    "date": "Mon, 22 Sep 2025",
    "draw_number": "4115",
    "winning_numbers": [
      "8",
      "15",
      "22",
      "24",
      "43",
      "47"
    ],
    "additional_number": "44",
    "jackpot": "$3,008,745",
    "group_prizes": [
      {
        "group": "Group 1",
        "amount": "-",
        "shares": "-"
      },
      {
        "group": "Group 2",
        "amount": "$142,474",
        "shares": "7"
      },
      {
        "group": "Group 3",
        "amount": "$2,005",
        "shares": "128"
      },
      {
        "group": "Group 4",
        "amount": "$392",
        "shares": "357"
      },
      {
        "group": "Group 5",
        "amount": "$50",
        "shares": "7,570"
      },
      {
        "group": "Group 6",
        "amount": "$25",
        "shares": "9,469"
      },
      {
        "group": "Group 7",
        "amount": "$10",
        "shares": "145,140"
      }
    ]
  },
  {
    "date": "Thu, 18 Sep 2025",
    "draw_number": "4114",
    "winning_numbers": [
      "6",
      "8",
      "9",
      "20",
      "45",
      "49"
    ],
    "additional_number": "21",
    "jackpot": "$1,236,374",
    "group_prizes": [
      {
        "group": "Group 1",
        "amount": "-",
        "shares": "-"
      },
      {
        "group": "Group 2",
        "amount": "-",
        "shares": "-"
      },
      {
        "group": "Group 3",
        "amount": "$1,193",
        "shares": "150"
      },
      {
        "group": "Group 4",
        "amount": "$296",
        "shares": "330"
      },
      {
        "group": "Group 5",
        "amount": "$50",
        "shares": "8,876"
      },
      {
        "group": "Group 6",
        "amount": "$25",
        "shares": "9,679"
      },
      {
        "group": "Group 7",
        "amount": "$10",
        "shares": "145,809"
      }
    ]
  },
  {
    "date": "Mon, 15 Sep 2025",
    "draw_number": "4113",
    "winning_numbers": [
      "10",
      "19",
      "25",
      "29",
      "33",
      "37"
    ],
    "additional_number": "24",
    "jackpot": "$2,956,471",
    "group_prizes": [
      {
        "group": "Group 1",
        "amount": "$2,956,471",
        "shares": "1"
      },
      {
        "group": "Group 2",
        "amount": "-",
        "shares": "-"
      },
      {
        "group": "Group 3",
        "amount": "$1,940",
        "shares": "129"
      },
      {
        "group": "Group 4",
        "amount": "$407",
        "shares": "336"
      },
      {
        "group": "Group 5",
        "amount": "$50",
        "shares": "7,473"
      },
      {
        "group": "Group 6",
        "amount": "$25",
        "shares": "9,754"
      },
      {
        "group": "Group 7",
        "amount": "$10",
        "shares": "141,348"
      }
    ]
  },
  {
    "date": "Thu, 11 Sep 2025",
    "draw_number": "4112",
    "winning_numbers": [
      "2",
      "15",
      "19",
      "35",
      "41",
      "48"
    ],
    "additional_number": "33",
    "jackpot": "$1,227,974",
    "group_prizes": [
      {
        "group": "Group 1",
        "amount": "-",
        "shares": "-"
      },
      {
        "group": "Group 2",
        "amount": "$129,261",
        "shares": "2"
      },
      {
        "group": "Group 3",
        "amount": "$1,954",
        "shares": "91"
      },
      {
        "group": "Group 4",
        "amount": "$443",
        "shares": "219"
      },
      {
        "group": "Group 5",
        "amount": "$50",
        "shares": "4,742"
      },
      {
        "group": "Group 6",
        "amount": "$25",
        "shares": "5,977"
      },
      {
        "group": "Group 7",
        "amount": "$10",
        "shares": "90,586"
      }
    ]
  },
  {
    "date": "Mon, 08 Sep 2025",
    "draw_number": "4111",
    "winning_numbers": [
      "1",
      "3",
      "33",
      "38",
      "39",
      "42"
    ],
    "additional_number": "31",
    "jackpot": "$1,306,245",
    "group_prizes": [
      {
        "group": "Group 1",
        "amount": "$1,306,245",
        "shares": "1"
      },
      {
        "group": "Group 2",
        "amount": "$137,500",
        "shares": "2"
      },
      {
        "group": "Group 3",
        "amount": "$1,767",
        "shares": "107"
      },
      {
        "group": "Group 4",
        "amount": "$355",
        "shares": "291"
      },
      {
        "group": "Group 5",
        "amount": "$50",
        "shares": "5,351"
      },
      {
        "group": "Group 6",
        "amount": "$25",
        "shares": "8,387"
      },
      {
        "group": "Group 7",
        "amount": "$10",
        "shares": "98,585"
      }
    ]
  },
  {
    "date": "Thu, 04 Sep 2025",
    "draw_number": "4110",
    "winning_numbers": [
      "8",
      "12",
      "21",
      "38",
      "40",
      "43"
    ],
    "additional_number": "25",
    "jackpot": "$3,074,780",
    "group_prizes": [
      {
        "group": "Group 1",
        "amount": "$3,074,781",
        "shares": "1"
      },
      {
        "group": "Group 2",
        "amount": "$191,022",
        "shares": "2"
      },
      {
        "group": "Group 3",
        "amount": "$1,476",
        "shares": "178"
      },
      {
        "group": "Group 4",
        "amount": "$415",
        "shares": "346"
      },
      {
        "group": "Group 5",
        "amount": "$50",
        "shares": "8,416"
      },
      {
        "group": "Group 6",
        "amount": "$25",
        "shares": "10,901"
      },
      {
        "group": "Group 7",
        "amount": "$10",
        "shares": "150,348"
      }
    ]
  },
  {
    "date": "Mon, 01 Sep 2025",
    "draw_number": "4109",
    "winning_numbers": [
      "3",
      "4",
      "8",
      "13",
      "14",
      "17"
    ],
    "additional_number": "20",
    "jackpot": "$1,260,079",
    "group_prizes": [
      {
        "group": "Group 1",
        "amount": "-",
        "shares": "-"
      },
      {
        "group": "Group 2",
        "amount": "$44,214",
        "shares": "6"
      },
      {
        "group": "Group 3",
        "amount": "$745",
        "shares": "245"
      },
      {
        "group": "Group 4",
        "amount": "$234",
        "shares": "426"
      },
      {
        "group": "Group 5",
        "amount": "$50",
        "shares": "9,103"
      },
      {
        "group": "Group 6",
        "amount": "$25",
        "shares": "10,611"
      },
      {
        "group": "Group 7",
        "amount": "$10",
        "shares": "142,655"
      }
    ]
  },
  {
    "date": "Thu, 28 Aug 2025",
    "draw_number": "4108",
    "winning_numbers": [
      "10",
      "11",
      "16",
      "24",
      "34",
      "35"
    ],
    "additional_number": "1",
    "jackpot": "$12,528,186",
    "group_prizes": [
      {
        "group": "Group 1",
        "amount": "$4,176,062",
        "shares": "3"
      },
      {
        "group": "Group 2",
        "amount": "$78,549",
        "shares": "18"
      },
      {
        "group": "Group 3",
        "amount": "$1,709",
        "shares": "569"
      },
      {
        "group": "Group 4",
        "amount": "$353",
        "shares": "1,505"
      },
      {
        "group": "Group 5",
        "amount": "$50",
        "shares": "29,745"
      },
      {
        "group": "Group 6",
        "amount": "$25",
        "shares": "43,639"
      },
      {
        "group": "Group 7",
        "amount": "$10",
        "shares": "544,163"
      }
    ]
  },
  {
    "date": "Mon, 25 Aug 2025",
    "draw_number": "4107",
    "winning_numbers": [
      "2",
      "3",
      "4",
      "16",
      "22",
      "39"
    ],
    "additional_number": "48",
    "jackpot": "$5,812,259",
    "group_prizes": [
      {
        "group": "Group 1",
        "amount": "-",
        "shares": "-"
      },
      {
        "group": "Group 2",
        "amount": "$119,475",
        "shares": "5"
      },
      {
        "group": "Group 3",
        "amount": "$1,850",
        "shares": "222"
      },
      {
        "group": "Group 4",
        "amount": "$395",
        "shares": "568"
      },
      {
        "group": "Group 5",
        "amount": "$50",
        "shares": "13,271"
      },
      {
        "group": "Group 6",
        "amount": "$25",
        "shares": "15,230"
      },
      {
        "group": "Group 7",
        "amount": "$10",
        "shares": "248,292"
      }
    ]
  },
  {
    "date": "Thu, 21 Aug 2025",
    "draw_number": "4106",
    "winning_numbers": [
      "4",
      "13",
      "22",
      "36",
      "38",
      "46"
    ],
    "additional_number": "12",
    "jackpot": "$2,974,742",
    "group_prizes": [
      {
        "group": "Group 1",
        "amount": "-",
        "shares": "-"
      },
      {
        "group": "Group 2",
        "amount": "$361,228",
        "shares": "1"
      },
      {
        "group": "Group 3",
        "amount": "$1,941",
        "shares": "128"
      },
      {
        "group": "Group 4",
        "amount": "$392",
        "shares": "346"
      },
      {
        "group": "Group 5",
        "amount": "$50",
        "shares": "6,532"
      },
      {
        "group": "Group 6",
        "amount": "$25",
        "shares": "9,643"
      },
      {
        "group": "Group 7",
        "amount": "$10",
        "shares": "125,956"
      }
    ]
  },
  {
    "date": "Mon, 18 Aug 2025",
    "draw_number": "4105",
    "winning_numbers": [
      "1",
      "4",
      "18",
      "24",
      "37",
      "42"
    ],
    "additional_number": "26",
    "jackpot": "$1,258,912",
    "group_prizes": [
      {
        "group": "Group 1",
        "amount": "-",
        "shares": "-"
      },
      {
        "group": "Group 2",
        "amount": "$132,518",
        "shares": "2"
      },
      {
        "group": "Group 3",
        "amount": "$1,719",
        "shares": "106"
      },
      {
        "group": "Group 4",
        "amount": "$373",
        "shares": "267"
      },
      {
        "group": "Group 5",
        "amount": "$50",
        "shares": "5,625"
      },
      {
        "group": "Group 6",
        "amount": "$25",
        "shares": "7,584"
      },
      {
        "group": "Group 7",
        "amount": "$10",
        "shares": "103,269"
      }
    ]
  },
  {
    "date": "Thu, 14 Aug 2025",
    "draw_number": "4104",
    "winning_numbers": [
      "22",
      "25",
      "29",
      "31",
      "34",
      "43"
    ],
    "additional_number": "11",
    "jackpot": "$2,980,746",
    "group_prizes": [
      {
        "group": "Group 1",
        "amount": "$2,980,746",
        "shares": "1"
      },
      {
        "group": "Group 2",
        "amount": "$209,176",
        "shares": "3"
      },
      {
        "group": "Group 3",
        "amount": "$1,778",
        "shares": "145"
      },
      {
        "group": "Group 4",
        "amount": "$354",
        "shares": "398"
      },
      {
        "group": "Group 5",
        "amount": "$50",
        "shares": "6,962"
      },
      {
        "group": "Group 6",
        "amount": "$25",
        "shares": "10,701"
      },
      {
        "group": "Group 7",
        "amount": "$10",
        "shares": "129,694"
      }
    ]
  },
  {
    "date": "Mon, 11 Aug 2025",
    "draw_number": "4103",
    "winning_numbers": [
      "9",
      "24",
      "31",
      "34",
      "43",
      "44"
    ],
    "additional_number": "1",
    "jackpot": "$1,199,651",
    "group_prizes": [
      {
        "group": "Group 1",
        "amount": "-",
        "shares": "-"
      },
      {
        "group": "Group 2",
        "amount": "-",
        "shares": "-"
      },
      {
        "group": "Group 3",
        "amount": "$1,809",
        "shares": "96"
      },
      {
        "group": "Group 4",
        "amount": "$467",
        "shares": "203"
      },
      {
        "group": "Group 5",
        "amount": "$50",
        "shares": "4,680"
      },
      {
        "group": "Group 6",
        "amount": "$25",
        "shares": "6,377"
      },
      {
        "group": "Group 7",
        "amount": "$10",
        "shares": "88,189"
      }
    ]
  },
  {
    "date": "Fri, 08 Aug 2025",
    "draw_number": "4102",
    "winning_numbers": [
      "2",
      "15",
      "28",
      "39",
      "42",
      "44"
    ],
    "additional_number": "5",
    "jackpot": "$5,527,890",
    "group_prizes": [
      {
        "group": "Group 1",
        "amount": "$5,527,890",
        "shares": "1"
      },
      {
        "group": "Group 2",
        "amount": "$241,107",
        "shares": "6"
      },
      {
        "group": "Group 3",
        "amount": "$1,896",
        "shares": "422"
      },
      {
        "group": "Group 4",
        "amount": "$401",
        "shares": "1,091"
      },
      {
        "group": "Group 5",
        "amount": "$50",
        "shares": "23,034"
      },
      {
        "group": "Group 6",
        "amount": "$25",
        "shares": "33,896"
      },
      {
        "group": "Group 7",
        "amount": "$10",
        "shares": "419,505"
      }
    ]
  },
  {
    "date": "Mon, 04 Aug 2025",
    "draw_number": "4101",
    "winning_numbers": [
      "30",
      "32",
      "40",
      "43",
      "45",
      "49"
    ],
    "additional_number": "5",
    "jackpot": "$1,343,651",
    "group_prizes": [
      {
        "group": "Group 1",
        "amount": "$1,343,651",
        "shares": "1"
      },
      {
        "group": "Group 2",
        "amount": "-",
        "shares": "-"
      },
      {
        "group": "Group 3",
        "amount": "$1,870",
        "shares": "104"
      },
      {
        "group": "Group 4",
        "amount": "$432",
        "shares": "246"
      },
      {
        "group": "Group 5",
        "amount": "$50",
        "shares": "5,369"
      },
      {
        "group": "Group 6",
        "amount": "$25",
        "shares": "7,154"
      },
      {
        "group": "Group 7",
        "amount": "$10",
        "shares": "92,419"
      }
    ]
  },
  {
    "date": "Thu, 31 Jul 2025",
    "draw_number": "4100",
    "winning_numbers": [
      "7",
      "19",
      "20",
      "21",
      "22",
      "29"
    ],
    "additional_number": "37",
    "jackpot": "$12,827,485",
    "group_prizes": [
      {
        "group": "Group 1",
        "amount": "$12,827,485",
        "shares": "1"
      },
      {
        "group": "Group 2",
        "amount": "$73,408",
        "shares": "20"
      },
      {
        "group": "Group 3",
        "amount": "$1,432",
        "shares": "705"
      },
      {
        "group": "Group 4",
        "amount": "$339",
        "shares": "1,626"
      },
      {
        "group": "Group 5",
        "amount": "$50",
        "shares": "36,754"
      },
      {
        "group": "Group 6",
        "amount": "$25",
        "shares": "40,890"
      },
      {
        "group": "Group 7",
        "amount": "$10",
        "shares": "626,904"
      }
    ]
  },
  {
    "date": "Mon, 28 Jul 2025",
    "draw_number": "4099",
    "winning_numbers": [
      "2",
      "14",
      "16",
      "21",
      "36",
      "47"
    ],
    "additional_number": "1",
    "jackpot": "$5,853,782",
    "group_prizes": [
      {
        "group": "Group 1",
        "amount": "-",
        "shares": "-"
      },
      {
        "group": "Group 2",
        "amount": "$121,727",
        "shares": "5"
      },
      {
        "group": "Group 3",
        "amount": "$1,920",
        "shares": "218"
      },
      {
        "group": "Group 4",
        "amount": "$418",
        "shares": "547"
      },
      {
        "group": "Group 5",
        "amount": "$50",
        "shares": "12,037"
      },
      {
        "group": "Group 6",
        "amount": "$25",
        "shares": "16,195"
      },
      {
        "group": "Group 7",
        "amount": "$10",
        "shares": "214,301"
      }
    ]
  },
  {
    "date": "Thu, 24 Jul 2025",
    "draw_number": "4098",
    "winning_numbers": [
      "9",
      "11",
      "24",
      "32",
      "39",
      "49"
    ],
    "additional_number": "26",
    "jackpot": "$2,962,788",
    "group_prizes": [
      {
        "group": "Group 1",
        "amount": "-",
        "shares": "-"
      },
      {
        "group": "Group 2",
        "amount": "$120,097",
        "shares": "3"
      },
      {
        "group": "Group 3",
        "amount": "$1,709",
        "shares": "145"
      },
      {
        "group": "Group 4",
        "amount": "$363",
        "shares": "373"
      },
      {
        "group": "Group 5",
        "amount": "$50",
        "shares": "8,784"
      },
      {
        "group": "Group 6",
        "amount": "$25",
        "shares": "10,526"
      },
      {
        "group": "Group 7",
        "amount": "$10",
        "shares": "153,533"
      }
    ]
  },
  {
    "date": "Mon, 21 Jul 2025",
    "draw_number": "4097",
    "winning_numbers": [
      "2",
      "5",
      "10",
      "12",
      "14",
      "37"
    ],
    "additional_number": "17",
    "jackpot": "$1,251,417",
    "group_prizes": [
      {
        "group": "Group 1",
        "amount": "-",
        "shares": "-"
      },
      {
        "group": "Group 2",
        "amount": "$65,865",
        "shares": "4"
      },
      {
        "group": "Group 3",
        "amount": "$1,098",
        "shares": "165"
      },
      {
        "group": "Group 4",
        "amount": "$219",
        "shares": "452"
      },
      {
        "group": "Group 5",
        "amount": "$50",
        "shares": "8,308"
      },
      {
        "group": "Group 6",
        "amount": "$25",
        "shares": "10,548"
      },
      {
        "group": "Group 7",
        "amount": "$10",
        "shares": "133,970"
      }
    ]
  },
  {
    "date": "Thu, 17 Jul 2025",
    "draw_number": "4096",
    "winning_numbers": [
      "7",
      "8",
      "17",
      "29",
      "32",
      "42"
    ],
    "additional_number": "1",
    "jackpot": "$12,766,543",
    "group_prizes": [
      {
        "group": "Group 1",
        "amount": "-",
        "shares": "-"
      },
      {
        "group": "Group 2",
        "amount": "$1,186,233",
        "shares": "12"
      },
      {
        "group": "Group 3",
        "amount": "$1,658",
        "shares": "609"
      },
      {
        "group": "Group 4",
        "amount": "$304",
        "shares": "1,815"
      },
      {
        "group": "Group 5",
        "amount": "$50",
        "shares": "34,527"
      },
      {
        "group": "Group 6",
        "amount": "$25",
        "shares": "49,068"
      },
      {
        "group": "Group 7",
        "amount": "$10",
        "shares": "614,079"
      }
    ]
  },
  {
    "date": "Mon, 14 Jul 2025",
    "draw_number": "4095",
    "winning_numbers": [
      "2",
      "8",
      "19",
      "29",
      "38",
      "41"
    ],
    "additional_number": "20",
    "jackpot": "$5,792,345",
    "group_prizes": [
      {
        "group": "Group 1",
        "amount": "-",
        "shares": "-"
      },
      {
        "group": "Group 2",
        "amount": "$67,336",
        "shares": "9"
      },
      {
        "group": "Group 3",
        "amount": "$1,478",
        "shares": "282"
      },
      {
        "group": "Group 4",
        "amount": "$334",
        "shares": "681"
      },
      {
        "group": "Group 5",
        "amount": "$50",
        "shares": "14,575"
      },
      {
        "group": "Group 6",
        "amount": "$25",
        "shares": "20,365"
      },
      {
        "group": "Group 7",
        "amount": "$10",
        "shares": "255,601"
      }
    ]
  },
  {
    "date": "Thu, 10 Jul 2025",
    "draw_number": "4094",
    "winning_numbers": [
      "12",
      "21",
      "26",
      "27",
      "35",
      "44"
    ],
    "additional_number": "10",
    "jackpot": "$2,913,763",
    "group_prizes": [
      {
        "group": "Group 1",
        "amount": "-",
        "shares": "-"
      },
      {
        "group": "Group 2",
        "amount": "$354,259",
        "shares": "1"
      },
      {
        "group": "Group 3",
        "amount": "$1,613",
        "shares": "151"
      },
      {
        "group": "Group 4",
        "amount": "$409",
        "shares": "325"
      },
      {
        "group": "Group 5",
        "amount": "$50",
        "shares": "6,941"
      },
      {
        "group": "Group 6",
        "amount": "$25",
        "shares": "10,924"
      },
      {
        "group": "Group 7",
        "amount": "$10",
        "shares": "133,227"
      }
    ]
  },
  {
    "date": "Mon, 07 Jul 2025",
    "draw_number": "4093",
    "winning_numbers": [
      "10",
      "15",
      "17",
      "33",
      "36",
      "45"
    ],
    "additional_number": "34",
    "jackpot": "$1,231,037",
    "group_prizes": [
      {
        "group": "Group 1",
        "amount": "-",
        "shares": "-"
      },
      {
        "group": "Group 2",
        "amount": "$129,583",
        "shares": "2"
      },
      {
        "group": "Group 3",
        "amount": "$2,376",
        "shares": "75"
      },
      {
        "group": "Group 4",
        "amount": "$421",
        "shares": "231"
      },
      {
        "group": "Group 5",
        "amount": "$50",
        "shares": "4,717"
      },
      {
        "group": "Group 6",
        "amount": "$25",
        "shares": "6,140"
      },
      {
        "group": "Group 7",
        "amount": "$10",
        "shares": "90,346"
      }
    ]
  },
  {
    "date": "Thu, 03 Jul 2025",
    "draw_number": "4092",
    "winning_numbers": [
      "6",
      "15",
      "16",
      "17",
      "25",
      "34"
    ],
    "additional_number": "31",
    "jackpot": "$2,894,419",
    "group_prizes": [
      {
        "group": "Group 1",
        "amount": "$2,894,419",
        "shares": "1"
      },
      {
        "group": "Group 2",
        "amount": "$175,398",
        "shares": "2"
      },
      {
        "group": "Group 3",
        "amount": "$1,556",
        "shares": "155"
      },
      {
        "group": "Group 4",
        "amount": "$330",
        "shares": "399"
      },
      {
        "group": "Group 5",
        "amount": "$50",
        "shares": "8,257"
      },
      {
        "group": "Group 6",
        "amount": "$25",
        "shares": "10,198"
      },
      {
        "group": "Group 7",
        "amount": "$10",
        "shares": "150,923"
      }
    ]
  },
  {
    "date": "Mon, 30 Jun 2025",
    "draw_number": "4091",
    "winning_numbers": [
      "11",
      "27",
      "31",
      "33",
      "34",
      "36"
    ],
    "additional_number": "13",
    "jackpot": "$1,228,144",
    "group_prizes": [
      {
        "group": "Group 1",
        "amount": "-",
        "shares": "-"
      },
      {
        "group": "Group 2",
        "amount": "$129,279",
        "shares": "2"
      },
      {
        "group": "Group 3",
        "amount": "$1,814",
        "shares": "98"
      },
      {
        "group": "Group 4",
        "amount": "$291",
        "shares": "334"
      },
      {
        "group": "Group 5",
        "amount": "$50",
        "shares": "5,439"
      },
      {
        "group": "Group 6",
        "amount": "$25",
        "shares": "8,592"
      },
      {
        "group": "Group 7",
        "amount": "$10",
        "shares": "96,224"
      }
    ]
  },
  {
    "date": "Thu, 26 Jun 2025",
    "draw_number": "4090",
    "winning_numbers": [
      "10",
      "26",
      "28",
      "35",
      "37",
      "46"
    ],
    "additional_number": "20",
    "jackpot": "$2,803,451",
    "group_prizes": [
      {
        "group": "Group 1",
        "amount": "$2,803,451",
        "shares": "1"
      },
      {
        "group": "Group 2",
        "amount": "$85,639",
        "shares": "4"
      },
      {
        "group": "Group 3",
        "amount": "$1,900",
        "shares": "124"
      },
      {
        "group": "Group 4",
        "amount": "$410",
        "shares": "314"
      },
      {
        "group": "Group 5",
        "amount": "$50",
        "shares": "7,271"
      },
      {
        "group": "Group 6",
        "amount": "$25",
        "shares": "9,136"
      },
      {
        "group": "Group 7",
        "amount": "$10",
        "shares": "125,256"
      }
    ]
  }
]